odoo/addons/energetica_cooperator/.gitignore
odoo/addons/energetica_cooperator/__init__.py
odoo/addons/energetica_cooperator/__manifest__.py
odoo/addons/energetica_cooperator/controllers/__init__.py
odoo/addons/energetica_cooperator/controllers/main.py
odoo/addons/energetica_cooperator/i18n/energetica_cooperator.pot
odoo/addons/energetica_cooperator/i18n/es.po
odoo/addons/energetica_cooperator/listeners/__init__.py
odoo/addons/energetica_cooperator/listeners/res_partner.py
odoo/addons/energetica_cooperator/models/__init__.py
odoo/addons/energetica_cooperator/models/res_company.py
odoo/addons/energetica_cooperator/models/res_partner.py
odoo/addons/energetica_cooperator/models/subscription_request.py
odoo/addons/energetica_cooperator/report/cooperator_certificat_G001.xml
odoo/addons/energetica_cooperator/views/res_company.xml
odoo/addons/energetica_cooperator/views/res_partner.xml
odoo/addons/energetica_cooperator/views/subscription_request.xml
odoo/addons/energetica_cooperator/views/subscription_template.xml
odoo_addon_energetica_cooperator-16.0.3.2.0.dist-info/METADATA
odoo_addon_energetica_cooperator-16.0.3.2.0.dist-info/WHEEL
odoo_addon_energetica_cooperator-16.0.3.2.0.dist-info/top_level.txt
odoo_addon_energetica_cooperator-16.0.3.2.0.dist-info/RECORD
