Metadata-Version: 2.1
Name: odoo-addon-energetica_cooperator
Version: 16.0.3.2.0
Requires-Python: >=3.10
Requires-Dist: odoo-addon-component_event>=16.0dev,<16.1dev
Requires-Dist: odoo-addon-cooperator>=16.0dev,<16.1dev
Requires-Dist: odoo-addon-cooperator_website>=16.0dev,<16.1dev
Requires-Dist: odoo>=16.0a,<16.1dev
Summary: Odoo customizations for Energetica Cooperator.
Home-page: https://coopdevs.org
License: AGPL-3
Author: Coopdevs Treball SCCL
Classifier: Programming Language :: Python
Classifier: Framework :: Odoo
Classifier: Framework :: Odoo :: 16.0
Classifier: License :: OSI Approved :: GNU Affero General Public License v3
